ninja_kafka_sdk/__init__.py
ninja_kafka_sdk/client.py
ninja_kafka_sdk/config.py
ninja_kafka_sdk/configure.py
ninja_kafka_sdk/exceptions.py
ninja_kafka_sdk/fix_partition_leadership.py
ninja_kafka_sdk/models.py
ninja_kafka_sdk/reset_partitions.py
ninja_kafka_sdk/self_healing.py
ninja_kafka_sdk/setup_current_config.py
ninja_kafka_sdk/simple_partition_tester.py
ninja_kafka_sdk-0.3.26.dist-info/METADATA
ninja_kafka_sdk-0.3.26.dist-info/WHEEL
ninja_kafka_sdk-0.3.26.dist-info/top_level.txt
ninja_kafka_sdk-0.3.26.dist-info/RECORD
