Metadata-Version: 2.4
Name: ninja-kafka-sdk
Version: 0.3.26
Summary: Kafka-based distributed task processing SDK
Author-email: Blazel Team <dev@blazel.ai>
Project-URL: Homepage, https://github.com/blazel/ninja-kafka-sdk
Project-URL: Bug Reports, https://github.com/blazel/ninja-kafka-sdk/issues
Project-URL: Source, https://github.com/blazel/ninja-kafka-sdk
Keywords: kafka,task-queue,distributed-computing,microservices,messaging
Classifier: Development Status :: 4 - Beta
Classifier: Intended Audience :: Developers
Classifier: License :: OSI Approved :: MIT License
Classifier: Operating System :: OS Independent
Classifier: Programming Language :: Python :: 3
Classifier: Programming Language :: Python :: 3.8
Classifier: Programming Language :: Python :: 3.9
Classifier: Programming Language :: Python :: 3.10
Classifier: Programming Language :: Python :: 3.11
Classifier: Topic :: Software Development :: Libraries :: Python Modules
Classifier: Topic :: System :: Distributed Computing
Classifier: Topic :: Software Development :: Libraries
Requires-Python: >=3.8
Requires-Dist: kafka-python>=2.0.0
Requires-Dist: psutil>=5.8.0
Requires-Dist: python-snappy==0.7.3
Provides-Extra: dev
Requires-Dist: pytest>=6.0; extra == "dev"
Requires-Dist: pytest-asyncio>=0.21.0; extra == "dev"
Requires-Dist: black>=22.0.0; extra == "dev"
Requires-Dist: isort>=5.0.0; extra == "dev"
